{"type":"Topology","arcs":[[[931,2450],[62,-13],[61,-65],[28,16],[64,-41],[24,43],[98,-118],[7,-103],[-6,5],[-64,35],[-72,-48],[-18,-61]],[[1115,2100],[-151,40],[-29,35],[3,52],[76,22],[-3,77],[-33,43],[-70,-23],[-44,-47],[-41,26],[-125,-30]],[[698,2295],[71,91],[31,104],[39,77],[27,10]],[[866,2577],[13,-87],[52,-40]],[[1114,2082],[20,-86]],[[1134,1996],[-149,-20],[-33,61],[79,37],[83,8]],[[1042,1150],[92,-43]],[[1134,1107],[-61,-96],[-41,-28],[-47,-139]],[[985,844],[-99,14],[-60,27],[-32,103],[5,84],[54,124],[47,-3],[142,-43]],[[368,1930],[-5,-21]],[[363,1909],[19,-79],[-86,-61]],[[296,1769],[-102,-56],[-27,-30],[-60,33]],[[107,1716],[-45,-8],[-23,82],[42,-22],[97,15],[7,55],[-33,66],[100,98],[-9,69]],[[243,2071],[105,56],[-15,-95],[8,-105],[27,3]],[[296,1769],[78,-67]],[[374,1702],[33,-69],[57,-20]],[[464,1613],[-173,-59],[-75,5],[-24,-30],[11,-97]],[[203,1432],[-36,12],[-60,81],[0,191]],[[841,1517],[46,-39],[23,-71],[-13,-32]],[[897,1375],[-28,-20],[-92,52],[39,43],[25,67]],[[698,2295],[-16,-76],[30,-70],[48,-21],[-106,-70],[0,-47],[-52,-70]],[[602,1941],[-48,-45],[-69,-23]],[[485,1873],[-14,41],[-85,-38],[-23,33]],[[368,1930],[57,162],[-19,122],[45,41],[26,62]],[[477,2317],[47,30],[33,-30],[72,19],[-15,101],[36,49],[-8,94],[58,70]],[[700,2650],[160,-20],[6,-53]],[[374,1702],[138,25]],[[512,1727],[52,18],[44,-91]],[[608,1654],[-144,-41]],[[485,1873],[-2,-67],[29,-79]],[[1016,1664],[68,-65],[-12,-51],[-39,-11],[-192,26]],[[841,1563],[-88,29],[21,65],[90,-24]],[[864,1633],[21,20],[92,-22],[39,33]],[[243,2071],[-111,-45],[-18,44],[-68,26],[-45,55],[79,83]],[[80,2234],[48,-15],[113,27],[100,1],[32,43],[66,-20],[38,47]],[[298,2811],[95,17],[38,-15],[57,-82],[70,-44],[142,-37]],[[80,2234],[106,28],[24,74],[75,25],[-9,40],[35,52],[-135,50],[-61,-30],[-46,-3],[-69,33],[24,52],[56,41],[83,30],[12,79],[96,39],[27,67]],[[1115,2100],[-1,-18]],[[1134,1996],[30,-35]],[[1164,1961],[-102,-23],[-37,12],[-29,-57],[-51,-12],[-17,-46]],[[928,1835],[-86,54],[-19,97],[-59,-20],[-162,-25]],[[1132,1699],[104,49],[-18,32]],[[1218,1780],[45,-52]],[[1263,1728],[-9,-44],[-49,-30],[-73,45]],[[985,844],[-71,-105],[-16,-53],[13,-64],[-42,-65],[2,-84],[37,-101],[30,-17]],[[938,355],[-101,-44],[-46,19],[-54,-76],[-128,-51]],[[609,203],[-8,102],[-26,62],[11,69],[-18,52],[-69,65]],[[499,553],[36,64],[10,68],[-80,67],[-52,-8]],[[413,744],[26,52]],[[439,796],[46,27],[-55,103]],[[430,926],[-14,76],[-115,154],[-4,102],[-52,74]],[[245,1332],[37,77],[42,46],[125,20],[69,-14],[76,51],[59,-10],[-8,79],[43,-5],[96,-45],[55,11]],[[839,1542],[2,-25]],[[897,1375],[96,0],[84,-21],[5,-133],[-40,-71]],[[609,199],[0,4]],[[938,355],[4,-120],[38,-77]],[[980,158],[-112,-42],[-44,15],[-13,-106]],[[811,25],[-46,22],[-14,60],[-68,77],[-74,15]],[[608,1654],[112,62],[87,-28]],[[807,1688],[57,-55]],[[841,1563],[-2,-21]],[[245,1332],[-42,100]],[[980,158],[-6,-89],[-55,21],[-85,-90],[-23,25]],[[1164,1961],[-5,-54],[58,-71],[1,-56]],[[1132,1699],[-138,-11]],[[994,1688],[-47,41]],[[947,1729],[22,65],[-41,41]],[[499,553],[-18,19],[-35,9],[-48,30],[-55,-3],[-37,41],[-77,-31],[-23,45],[42,153],[46,-3],[45,-48],[74,-21]],[[439,796],[-77,87],[-76,46],[-16,55],[54,40],[-91,66],[-65,23],[-9,93],[64,-2],[-3,-55],[86,-102],[83,-63],[41,-58]],[[1016,1664],[-22,24]],[[1263,1728],[72,-35],[89,3],[14,-51],[-26,-114],[-56,-40],[24,-61],[65,29],[33,-21],[60,-109],[-60,-15],[-31,41],[-100,-45],[-23,-108],[-133,-32],[-57,-63]],[[807,1688],[57,37],[83,4]]],"bbox":[14.780273722574691,36.65005810567073,15.337442727354555,37.41343493703923],"transform":{"scale":[0.00036226853366701147,0.0002699352303283228],"translate":[14.780273722574691,36.65005810567073]},"objects":{"comuni":{"type":"GeometryCollection","geometries":[{"arcs":[[[0,1,2,3]],[[4,5]]],"type":"MultiPolygon","properties":{"cod_com":89001,"denominazione":"Augusta"}},{"arcs":[[6,7,8]],"type":"Polygon","properties":{"cod_com":89002,"denominazione":"Avola"}},{"arcs":[[9,10,11,12,13]],"type":"Polygon","properties":{"cod_com":89003,"denominazione":"Buccheri"}},{"arcs":[[-12,14,15,16,17]],"type":"Polygon","properties":{"cod_com":89004,"denominazione":"Buscemi"}},{"arcs":[[18,19]],"type":"Polygon","properties":{"cod_com":89005,"denominazione":"Canicattini Bagni"}},{"arcs":[[-3,20,21,22,-10,23,24,25]],"type":"Polygon","properties":{"cod_com":89006,"denominazione":"Carlentini"}},{"arcs":[[-16,26,27,28]],"type":"Polygon","properties":{"cod_com":89007,"denominazione":"Cassaro"}},{"arcs":[[-11,-23,29,-27,-15]],"type":"Polygon","properties":{"cod_com":89008,"denominazione":"Ferla"}},{"arcs":[[30,31,32]],"type":"Polygon","properties":{"cod_com":89009,"denominazione":"Floridia"}},{"arcs":[[-14,33,34,-24]],"type":"Polygon","properties":{"cod_com":89010,"denominazione":"Francofonte"}},{"arcs":[[35,-25,-35,36]],"type":"Polygon","properties":{"cod_com":89011,"denominazione":"Lentini"}},{"arcs":[[[-2,37,-6,38,39,40,-21]],[[41,42,43]]],"type":"MultiPolygon","properties":{"cod_com":89012,"denominazione":"Melilli"}},{"arcs":[[-9,44,45,46,47,48,49,50,51,52,-20,53]],"type":"Polygon","properties":{"cod_com":89013,"denominazione":"Noto"}},{"arcs":[[54,-46,55,56,57]],"type":"Polygon","properties":{"cod_com":89014,"denominazione":"Pachino"}},{"arcs":[[-17,-29,58,59,-32,60,-52,61]],"type":"Polygon","properties":{"cod_com":89015,"denominazione":"Palazzolo Acreide"}},{"arcs":[[-57,62]],"type":"Polygon","properties":{"cod_com":89020,"denominazione":"Portopalo di Capo Passero"}},{"arcs":[[-40,63,-42,64,65,66]],"type":"Polygon","properties":{"cod_com":89021,"denominazione":"Priolo Gargallo"}},{"arcs":[[[67,-48]],[[68,-50]]],"type":"MultiPolygon","properties":{"cod_com":89016,"denominazione":"Rosolini"}},{"arcs":[[-7,-54,-19,-53,-61,-31,69,-65,-44,70]],"type":"Polygon","properties":{"cod_com":89017,"denominazione":"Siracusa"}},{"arcs":[[-33,-60,71,-66,-70]],"type":"Polygon","properties":{"cod_com":89018,"denominazione":"Solarino"}},{"arcs":[[-22,-41,-67,-72,-59,-28,-30]],"type":"Polygon","properties":{"cod_com":89019,"denominazione":"Sortino"}}]}}}